[
{"item_id": "5004300127", "store_number": "0416", "zip_code": "28278", "date": "2024-11-21T13:04:43.486418Z", "url": "https://www.lowes.com/pd/National-Tree-Company-0-5-ft-24-in-Pre-lit-Battery-operated-Harvest-Artificial-Wreath/5004300127", "model_number": "HC7-104-24W", "brand": "National Tree Company", "price_hidden_in_cart": false, "price": 49.98},
{"item_id": "5013823317", "store_number": "0416", "zip_code": "28278", "date": "2024-11-21T13:04:45.838987Z", "url": "https://www.lowes.com/pd/Nearly-Natural-6-ft-Harvest-Artificial-Garland/5013823317", "model_number": "W1236", "brand": "Nearly Natural", "price_hidden_in_cart": false, "price": 74.98},
{"item_id": "5015205587", "store_number": "0416", "zip_code": "28278", "date": "2024-11-21T13:04:47.002953Z", "url": "https://www.lowes.com/pd/Northlight-0-5-ft-28-in-Harvest-Artificial-Wreath/5015205587", "model_number": "35762375", "brand": "Northlight", "price_hidden_in_cart": false, "price": 74.98},
{"item_id": "5000293507", "store_number": "0416", "zip_code": "28278", "date": "2024-11-21T13:04:48.233931Z", "url": "https://www.lowes.com/pd/Worth-Imports-20-in-Bittersweet-Wreath-On-Natural-Twig-Base/5000293507", "model_number": "7771", "brand": "Worth Imports", "price_hidden_in_cart": false, "price": 37.98},
{"item_id": "5015355061", "store_number": "0416", "zip_code": "28278", "date": "2024-11-21T13:04:49.771815Z", "url": "https://www.lowes.com/pd/Worth-Imports-2-5-ft-30-in-Berries-Artificial-Wreath/5015355061", "model_number": "9984", "brand": "Worth Imports", "price_hidden_in_cart": false, "price": 79.48},
{"item_id": "5015205597", "store_number": "0416", "zip_code": "28278", "date": "2024-11-21T13:04:50.757411Z", "url": "https://www.lowes.com/pd/Northlight-0-5-ft-26-in-Harvest-Artificial-Wreath/5015205597", "model_number": "35762344", "brand": "Northlight", "price_hidden_in_cart": false, "price": 85.98},
{"item_id": "5013823411", "store_number": "0416", "zip_code": "28278", "date": "2024-11-21T13:04:51.575866Z", "url": "https://www.lowes.com/pd/Nearly-Natural-2-8-ft-Pumpkin-Artificial-Swag/5013823411", "model_number": "W1241", "brand": "Nearly Natural", "price_hidden_in_cart": false, "price": 36.61},
{"item_id": "5013805357", "store_number": "0416", "zip_code": "28278", "date": "2024-11-21T13:04:53.113052Z", "url": "https://www.lowes.com/pd/Worth-Imports-21-in-Fall-Berries-And-Leaves-Wreath/5013805357", "model_number": "9934", "brand": "Worth Imports", "price_hidden_in_cart": false, "price": 43.89},
{"item_id": "5013823403", "store_number": "0416", "zip_code": "28278", "date": "2024-11-21T13:04:54.545167Z", "url": "https://www.lowes.com/pd/Nearly-Natural-2-ft-24-in-Leaves-Artificial-Wreath/5013823403", "model_number": "W1238", "brand": "Nearly Natural", "price_hidden_in_cart": false, "price": 65.63},
{"item_id": "5013823289", "store_number": "0416", "zip_code": "28278", "date": "2024-11-21T13:04:55.670328Z", "url": "https://www.lowes.com/pd/Nearly-Natural-5-ft-Pumpkin-Artificial-Garland/5013823289", "model_number": "W1242", "brand": "Nearly Natural", "price_hidden_in_cart": false, "price": 54.93},
{"item_id": "5014645853", "store_number": "0416", "zip_code": "28278", "date": "2024-11-21T13:04:56.992063Z", "url": "https://www.lowes.com/pd/National-Tree-Company-14-in-Harvest-Lantern-with-Sunflower-Mixed-Leaves-Berry-and-Pumpkins-1-Warm-White-Battery-Operated-LED-Candle/5014645853", "model_number": "RAHV-1006SK4019", "brand": "National Tree Company", "price_hidden_in_cart": false, "price": 45},
{"item_id": "5015205675", "store_number": "0416", "zip_code": "28278", "date": "2024-11-21T13:04:58.333222Z", "url": "https://www.lowes.com/pd/Northlight-0-5-ft-26-in-Harvest-Artificial-Wreath/5015205675", "model_number": "35762345", "brand": "Northlight", "price_hidden_in_cart": false, "price": 62.98},
{"item_id": "5012906989", "store_number": "0416", "zip_code": "28278", "date": "2024-11-21T13:04:59.663976Z", "url": "https://www.lowes.com/pd/Gerson-International-Liven-up-your-front-door-with-this-22-D-Harvest-Wreath-featuring-fall-leaves-berries-and-orange-sunflower-accents/5012906989", "model_number": "2492690EC", "brand": "Gerson International", "price_hidden_in_cart": false, "price": 45},
{"item_id": "5000119951", "store_number": "0416", "zip_code": "28278", "date": "2024-11-21T13:05:00.756627Z", "url": "https://www.lowes.com/pd/Worth-Imports-22-in-Sunflower-Leaf-and-Pumpkin-Teardrop/5000119951", "model_number": "7377", "brand": "Worth Imports", "price_hidden_in_cart": false, "price": 21.23},
{"item_id": "5000032071", "store_number": "0416", "zip_code": "28278", "date": "2024-11-21T13:05:01.815549Z", "url": "https://www.lowes.com/pd/Worth-Imports-14-in-Acorn-and-Leaf-Wreath/5000032071", "model_number": "5309", "brand": "Worth Imports", "price_hidden_in_cart": false, "price": 25.69},
{"item_id": "5013548227", "store_number": "0416", "zip_code": "28278", "date": "2024-11-21T13:05:03.251132Z", "url": "https://www.lowes.com/pd/Nearly-Natural-2-3-ft-28-in-Harvest-Artificial-Wreath/5013548227", "model_number": "W1186", "brand": "Nearly Natural", "price_hidden_in_cart": false, "price": 67.19},
{"item_id": "5000269109", "store_number": "0416", "zip_code": "28278", "date": "2024-11-21T13:05:04.581637Z", "url": "https://www.lowes.com/pd/Worth-Imports-26-in-Fall-Twig-Teardrop-with-Long-Grasses-Berries-Pumpkins-and-Leaves/5000269109", "model_number": "7726", "brand": "Worth Imports", "price_hidden_in_cart": false, "price": 18.97},
{"item_id": "5015205579", "store_number": "0416", "zip_code": "28278", "date": "2024-11-21T13:05:05.808240Z", "url": "https://www.lowes.com/pd/Northlight-0-58-ft-24-in-Harvest-Artificial-Wreath/5015205579", "model_number": "35762377", "brand": "Northlight", "price_hidden_in_cart": false, "price": 62.98},
{"item_id": "5013823361", "store_number": "0416", "zip_code": "28278", "date": "2024-11-21T13:05:07.138994Z", "url": "https://www.lowes.com/pd/Nearly-Natural-2-2-ft-26-in-Harvest-Artificial-Wreath/5013823361", "model_number": "W1224", "brand": "Nearly Natural", "price_hidden_in_cart": false, "price": 48.71},
{"item_id": "5004299999", "store_number": "0416", "zip_code": "28278", "date": "2024-11-21T13:05:08.164754Z", "url": "https://www.lowes.com/pd/National-Tree-Company-6-ft-Pumpkin-Artificial-Garland/5004299999", "model_number": "RAHV-G060669A", "brand": "National Tree Company", "price_hidden_in_cart": false, "price": 42.74},
{"item_id": "5005471241", "store_number": "0416", "zip_code": "28278", "date": "2024-11-21T13:05:09.700075Z", "url": "https://www.lowes.com/pd/Glitzhome-18-5-in-D-Fall-Fabric-Plaid-Wreath/5005471241", "model_number": "2005500067", "brand": "Glitzhome", "price_hidden_in_cart": false, "price": 40.46},
{"item_id": "1000792934", "store_number": "0416", "zip_code": "28278", "date": "2024-11-21T13:05:10.884544Z", "url": "https://www.lowes.com/pd/Nearly-Natural-28-in-Russet-Gold-Indoor-Leaf-Artificial-Thanksgiving-Wreath/1000792934", "model_number": "4648", "brand": "Nearly Natural", "price_hidden_in_cart": false, "price": 87.45},
{"item_id": "5005470873", "store_number": "0416", "zip_code": "28278", "date": "2024-11-21T13:05:12.056974Z", "url": "https://www.lowes.com/pd/Glitzhome-24-in-D-Fall-Lighted-Maple-Leaves-Wreath/5005470873", "model_number": "2019500005", "brand": "Glitzhome", "price_hidden_in_cart": false, "price": 35.19},
{"item_id": "5000119949", "store_number": "0416", "zip_code": "28278", "date": "2024-11-21T13:05:13.287114Z", "url": "https://www.lowes.com/pd/Worth-Imports-18-in-Fall-Berry-Wreath-W-Foliage/5000119949", "model_number": "7370", "brand": "Worth Imports", "price_hidden_in_cart": false, "price": 29.98},
{"item_id": "5013823247", "store_number": "0416", "zip_code": "28278", "date": "2024-11-21T13:05:16.750263Z", "url": "https://www.lowes.com/pd/Nearly-Natural-2-ft-24-in-Harvest-Artificial-Wreath/5013823247", "model_number": "W1243", "brand": "Nearly Natural", "price_hidden_in_cart": false, "price": 59.38},
{"item_id": "5015205639", "store_number": "0416", "zip_code": "28278", "date": "2024-11-21T13:05:17.483860Z", "url": "https://www.lowes.com/pd/Northlight-5-ft-Harvest-Artificial-Garland/5015205639", "model_number": "34868423", "brand": "Northlight", "price_hidden_in_cart": false, "price": 53.98},
{"item_id": "5015355081", "store_number": "0416", "zip_code": "28278", "date": "2024-11-21T13:05:18.814768Z", "url": "https://www.lowes.com/pd/Worth-Imports-1-83-ft-22-in-Pumpkin-Artificial-Wreath/5015355081", "model_number": "9978", "brand": "Worth Imports", "price_hidden_in_cart": false, "price": 73.98},
{"item_id": "5015161629", "store_number": "0416", "zip_code": "28278", "date": "2024-11-21T13:05:20.027114Z", "url": "https://www.lowes.com/pd/Sullivans-0-9-ft-11-in-Berries-Artificial-Wreath/5015161629", "model_number": "23091CR", "brand": "Sullivans", "price_hidden_in_cart": false, "price": 28.98},
{"item_id": "5014645867", "store_number": "0416", "zip_code": "28278", "date": "2024-11-21T13:05:21.260470Z", "url": "https://www.lowes.com/pd/National-Tree-Company-2-ft-22-in-Harvest-Artificial-Wreath/5014645867", "model_number": "RAHV-0KW061029A", "brand": "National Tree Company", "price_hidden_in_cart": false, "price": 65.98},
{"item_id": "1003258842", "store_number": "0416", "zip_code": "28278", "date": "2024-11-21T13:05:22.811267Z", "url": "https://www.lowes.com/pd/Nearly-Natural-24-in-Fatsia-with-Berries-Autumn-Artificial-Wreath/1003258842", "model_number": "4474", "brand": "Nearly Natural", "price_hidden_in_cart": false, "price": 38.75},
{"item_id": "5013823381", "store_number": "0416", "zip_code": "28278", "date": "2024-11-21T13:05:23.957525Z", "url": "https://www.lowes.com/pd/Nearly-Natural-1-7-ft-20-in-Pumpkin-Artificial-Wreath/5013823381", "model_number": "W1250", "brand": "Nearly Natural", "price_hidden_in_cart": false, "price": 39.94},
{"item_id": "5013548457", "store_number": "0416", "zip_code": "28278", "date": "2024-11-21T13:05:24.841675Z", "url": "https://www.lowes.com/pd/Nearly-Natural-22-in-Leaves-Artificial-Wreath/5013548457", "model_number": "W1216", "brand": "Nearly Natural", "price_hidden_in_cart": false, "price": 43.65},
{"item_id": "5013801335", "store_number": "0416", "zip_code": "28278", "date": "2024-11-21T13:05:27.038039Z", "url": "https://www.lowes.com/pd/Northlight-24-in-Green-Autumn-Harvest-Artificial-Thanksgiving-Wreath-with-Pumpkins-and-Gourds-Indoor-Use/5013801335", "model_number": "33532675", "brand": "Northlight", "price_hidden_in_cart": false, "price": 80.98},
{"item_id": "5013823387", "store_number": "0416", "zip_code": "28278", "date": "2024-11-21T13:05:27.301780Z", "url": "https://www.lowes.com/pd/Nearly-Natural-2-9-ft-Leaves-Artificial-Swag/5013823387", "model_number": "W1231", "brand": "Nearly Natural", "price_hidden_in_cart": false, "price": 35.47},
{"item_id": "5000215063", "store_number": "0416", "zip_code": "28278", "date": "2024-11-21T13:05:28.341561Z", "url": "https://www.lowes.com/pd/Worth-Imports-24-in-Cotton-W-L-V-S-Wreath/5000215063", "model_number": "3284", "brand": "Worth Imports", "price_hidden_in_cart": false, "price": 49.12},
{"item_id": "5000205253", "store_number": "0416", "zip_code": "28278", "date": "2024-11-21T13:05:29.773375Z", "url": "https://www.lowes.com/pd/Worth-Imports-20-in-Maple-Leaf-and-Berry-Wreath/5000205253", "model_number": "7779", "brand": "Worth Imports", "price_hidden_in_cart": false, "price": 23.99},
{"item_id": "5002008989", "store_number": "0416", "zip_code": "28278", "date": "2024-11-21T13:05:31.205921Z", "url": "https://www.lowes.com/pd/Worth-Imports-5-Mini-Chinese-Lantern-Garland/5002008989", "model_number": "7183", "brand": "Worth Imports", "price_hidden_in_cart": false, "price": 25.48},
{"item_id": "5015161813", "store_number": "0416", "zip_code": "28278", "date": "2024-11-21T13:05:32.538011Z", "url": "https://www.lowes.com/pd/Sullivans-1-ft-12-in-Leaves-Artificial-Wreath/5015161813", "model_number": "MXFA4", "brand": "Sullivans", "price_hidden_in_cart": false, "price": 26.98},
{"item_id": "5015377359", "store_number": "0416", "zip_code": "28278", "date": "2024-11-21T13:05:33.968985Z", "url": "https://www.lowes.com/pd/Sullivans-1-3-ft-15-in-Harvest-Artificial-Wreath/5015377359", "model_number": "BRE4", "brand": "Sullivans", "price_hidden_in_cart": false, "price": 28.98},
{"item_id": "5001425175", "store_number": "0416", "zip_code": "28278", "date": "2024-11-21T13:05:37.042743Z", "url": "https://www.lowes.com/pd/Fraser-Hill-Farm-Indoor-or-Outdoor-9-ft-Mixed-Green-Garland-with-Pink/5001425175", "model_number": "FF108HVGL002-0MLT", "brand": "Fraser Hill Farm", "price_hidden_in_cart": false, "price": 40.16},
{"item_id": "5014645859", "store_number": "0416", "zip_code": "28278", "date": "2024-11-21T13:05:38.171217Z", "url": "https://www.lowes.com/pd/National-Tree-Company-2-ft-24-in-Harvest-Artificial-Wreath/5014645859", "model_number": "RAHV-0AW060751A", "brand": "National Tree Company", "price_hidden_in_cart": false, "price": 68.98},
{"item_id": "5015205563", "store_number": "0416", "zip_code": "28278", "date": "2024-11-21T13:05:38.885344Z", "url": "https://www.lowes.com/pd/Northlight-1-83-ft-22-in-Harvest-Artificial-Wreath/5015205563", "model_number": "35182617", "brand": "Northlight", "price_hidden_in_cart": false, "price": 74.98},
{"item_id": "5005581955", "store_number": "0416", "zip_code": "28278", "date": "2024-11-21T13:05:39.875231Z", "url": "https://www.lowes.com/pd/Northlight-26-Autumn-Harvest-Berries-and-Pumpkin-Artificial-Teardrop-Swag/5005581955", "model_number": "32257217", "brand": "Northlight", "price_hidden_in_cart": false, "price": 27.48},
{"item_id": "5015205663", "store_number": "0416", "zip_code": "28278", "date": "2024-11-21T13:05:41.649892Z", "url": "https://www.lowes.com/pd/Northlight-0-5-ft-24-in-Harvest-Artificial-Wreath/5015205663", "model_number": "34868419", "brand": "Northlight", "price_hidden_in_cart": false, "price": 70.98},
{"item_id": "5012907389", "store_number": "0416", "zip_code": "28278", "date": "2024-11-21T13:05:42.471954Z", "url": "https://www.lowes.com/pd/Puleo-International-2-5-ft-30-in-Artificial-Wreath/5012907389", "model_number": "305-1390A-W30", "brand": "Puleo International", "price_hidden_in_cart": false, "price": 174.7},
{"item_id": "5013823199", "store_number": "0416", "zip_code": "28278", "date": "2024-11-21T13:05:44.005593Z", "url": "https://www.lowes.com/pd/Nearly-Natural-2-5-ft-30-in-Pumpkin-Artificial-Wreath/5013823199", "model_number": "W1184", "brand": "Nearly Natural", "price_hidden_in_cart": false, "price": 72.44},
{"item_id": "5015355005", "store_number": "0416", "zip_code": "28278", "date": "2024-11-21T13:05:44.826294Z", "url": "https://www.lowes.com/pd/Worth-Imports-6-ft-Pumpkin-Artificial-Garland/5015355005", "model_number": "9140", "brand": "Worth Imports", "price_hidden_in_cart": false, "price": 79.48},
{"item_id": "5015205657", "store_number": "0416", "zip_code": "28278", "date": "2024-11-21T13:05:45.849138Z", "url": "https://www.lowes.com/pd/Northlight-5-ft-Harvest-Artificial-Garland/5015205657", "model_number": "34868427", "brand": "Northlight", "price_hidden_in_cart": false, "price": 51.98},
{"item_id": "1003252376", "store_number": "0416", "zip_code": "28278", "date": "2024-11-21T13:05:47.488104Z", "url": "https://www.lowes.com/pd/Gerson-International-22-in-Diameter-Harvest-Wreath-with-Fall-Flowers-and-Berries/1003252376", "model_number": "2539950EC", "brand": "Gerson International", "price_hidden_in_cart": false, "price": 53.98},
{"item_id": "5014611585", "store_number": "0416", "zip_code": "28278", "date": "2024-11-21T13:05:48.616505Z", "url": "https://www.lowes.com/pd/Worth-Imports-5-5-ft-66-in-Leaves-Artificial-Garland/5014611585", "model_number": "9117", "brand": "Worth Imports", "price_hidden_in_cart": false, "price": 28.98},
{"item_id": "5013583283", "store_number": "0416", "zip_code": "28278", "date": "2024-11-21T13:05:49.912306Z", "url": "https://www.lowes.com/pd/Glitzhome-Handmade-Fall-Thanksgiving-Artificial-Garland-Multi-Colored-11-Balls-3-07-in-Diameter-Indoor-Use-Thanksgiving-Decor/5013583283", "model_number": "2029800002", "brand": "Glitzhome", "price_hidden_in_cart": false, "price": 30.48},
{"item_id": "5015354971", "store_number": "0416", "zip_code": "28278", "date": "2024-11-21T13:05:51.484335Z", "url": "https://www.lowes.com/pd/Worth-Imports-5-41-ft-Pumpkin-Artificial-Garland/5015354971", "model_number": "9126", "brand": "Worth Imports", "price_hidden_in_cart": false, "price": 28.98},
{"item_id": "5015205647", "store_number": "0416", "zip_code": "28278", "date": "2024-11-21T13:05:52.607799Z", "url": "https://www.lowes.com/pd/Northlight-0-5-ft-Harvest-Artificial-Swag/5015205647", "model_number": "34868446", "brand": "Northlight", "price_hidden_in_cart": false, "price": 23.98},
{"item_id": "5015161685", "store_number": "0416", "zip_code": "28278", "date": "2024-11-21T13:05:53.530896Z", "url": "https://www.lowes.com/pd/Sullivans-0-8-ft-10-in-Berries-Artificial-Wreath/5015161685", "model_number": "BTTSW4", "brand": "Sullivans", "price_hidden_in_cart": false, "price": 26.98},
{"item_id": "5013823401", "store_number": "0416", "zip_code": "28278", "date": "2024-11-21T13:05:55.061282Z", "url": "https://www.lowes.com/pd/Nearly-Natural-2-ft-24-in-Leaves-Artificial-Wreath/5013823401", "model_number": "W1232", "brand": "Nearly Natural", "price_hidden_in_cart": false, "price": 58.94},
{"item_id": "1003258848", "store_number": "0416", "zip_code": "28278", "date": "2024-11-21T13:05:55.785548Z", "url": "https://www.lowes.com/pd/Nearly-Natural-6ft-Autumn-Magnolia-Leaf-and-Berries-Artificial-Garland/1003258848", "model_number": "4497", "brand": "Nearly Natural", "price_hidden_in_cart": false, "price": 47.31},
{"item_id": "5000110691", "store_number": "0416", "zip_code": "28278", "date": "2024-11-21T13:05:57.113506Z", "url": "https://www.lowes.com/pd/Worth-Imports-60-in-Bittersweet-Garland/5000110691", "model_number": "7147", "brand": "Worth Imports", "price_hidden_in_cart": false, "price": 35},
{"item_id": "5004300021", "store_number": "0416", "zip_code": "28278", "date": "2024-11-21T13:05:57.993253Z", "url": "https://www.lowes.com/pd/National-Tree-Company-2-ft-24-in-Harvest-Artificial-Wreath/5004300021", "model_number": "RAHV-ABN71202", "brand": "National Tree Company", "price_hidden_in_cart": false, "price": 50.6},
{"item_id": "5015355179", "store_number": "0416", "zip_code": "28278", "date": "2024-11-21T13:05:59.059333Z", "url": "https://www.lowes.com/pd/Worth-Imports-2-08-ft-Pumpkin-Artificial-Swag/5015355179", "model_number": "9987", "brand": "Worth Imports", "price_hidden_in_cart": false, "price": 45},
{"item_id": "5004299603", "store_number": "0416", "zip_code": "28278", "date": "2024-11-21T13:06:00.186425Z", "url": "https://www.lowes.com/pd/National-Tree-Company-2-ft-22-in-Harvest-Artificial-Wreath/5004299603", "model_number": "RAHV-15560W22", "brand": "National Tree Company", "price_hidden_in_cart": false, "price": 55.98},
{"item_id": "5013548339", "store_number": "0416", "zip_code": "28278", "date": "2024-11-21T13:06:00.596508Z", "url": "https://www.lowes.com/pd/Nearly-Natural-2-5-ft-30-in-Harvest-Artificial-Wreath/5013548339", "model_number": "W1180", "brand": "Nearly Natural", "price_hidden_in_cart": false, "price": 74.63},
{"item_id": "5014356695", "store_number": "0416", "zip_code": "28278", "date": "2024-11-21T13:06:01.928901Z", "url": "https://www.lowes.com/pd/Northlight-24-in-Green-Indoor-Hanging-Artificial-Wreath/5014356695", "model_number": "35644463", "brand": "Northlight", "price_hidden_in_cart": false, "price": 85.48},
{"item_id": "5014595005", "store_number": "0416", "zip_code": "28278", "date": "2024-11-21T13:06:02.957592Z", "url": "https://www.lowes.com/pd/Worth-Imports-2-ft-24-in-Pumpkin-Artificial-Wreath/5014595005", "model_number": "9970", "brand": "Worth Imports", "price_hidden_in_cart": false, "price": 109},
{"item_id": "5002009407", "store_number": "0416", "zip_code": "28278", "date": "2024-11-21T13:06:04.169712Z", "url": "https://www.lowes.com/pd/Worth-Imports-Fall-15-Pine-Cone-And-Wood-Curl-Wreath/5002009407", "model_number": "9900", "brand": "Worth Imports", "price_hidden_in_cart": false, "price": 31.98},
{"item_id": "5015355065", "store_number": "0416", "zip_code": "28278", "date": "2024-11-21T13:06:05.285760Z", "url": "https://www.lowes.com/pd/Worth-Imports-6-ft-Leaves-Artificial-Garland/5015355065", "model_number": "9139", "brand": "Worth Imports", "price_hidden_in_cart": false, "price": 34.48},
{"item_id": "5015205703", "store_number": "0416", "zip_code": "28278", "date": "2024-11-21T13:06:06.738580Z", "url": "https://www.lowes.com/pd/Northlight-0-92-ft-20-in-Harvest-Artificial-Wreath/5015205703", "model_number": "34315256", "brand": "Northlight", "price_hidden_in_cart": false, "price": 37.98},
{"item_id": "5000137901", "store_number": "0416", "zip_code": "28278", "date": "2024-11-21T13:06:07.660690Z", "url": "https://www.lowes.com/pd/Worth-Imports-36-in-Fall-Maple-Leaf-Swag-W-Pumpkin/5000137901", "model_number": "7707", "brand": "Worth Imports", "price_hidden_in_cart": false, "price": 39.99},
{"item_id": "1003258866", "store_number": "0416", "zip_code": "28278", "date": "2024-11-21T13:06:09.403016Z", "url": "https://www.lowes.com/pd/Nearly-Natural-21-in-Autumn-Fern-Artificial-Wreath/1003258866", "model_number": "W1127", "brand": "Nearly Natural", "price_hidden_in_cart": false, "price": 40.91},
{"item_id": "5004301637", "store_number": "0416", "zip_code": "28278", "date": "2024-11-21T13:06:10.324602Z", "url": "https://www.lowes.com/pd/National-Tree-Company/5004301637", "model_number": "RAHV-W060630A", "brand": "National Tree Company", "price_hidden_in_cart": false, "price": 39.98},
{"item_id": "5014645887", "store_number": "0416", "zip_code": "28278", "date": "2024-11-21T13:06:11.963631Z", "url": "https://www.lowes.com/pd/National-Tree-Company-2-ft-22-in-Harvest-Artificial-Wreath/5014645887", "model_number": "RAHV-DA102W-1", "brand": "National Tree Company", "price_hidden_in_cart": false, "price": 44.88},
{"item_id": "5015355055", "store_number": "0416", "zip_code": "28278", "date": "2024-11-21T13:06:12.898361Z", "url": "https://www.lowes.com/pd/Worth-Imports-1-75-ft-21-in-Leaves-Artificial-Wreath/5015355055", "model_number": "9991", "brand": "Worth Imports", "price_hidden_in_cart": false, "price": 60.48},
{"item_id": "5015205617", "store_number": "0416", "zip_code": "28278", "date": "2024-11-21T13:06:14.317845Z", "url": "https://www.lowes.com/pd/Northlight-0-5-ft-26-in-Harvest-Artificial-Wreath/5015205617", "model_number": "35762346", "brand": "Northlight", "price_hidden_in_cart": false, "price": 73.98},
{"item_id": "5015355121", "store_number": "0416", "zip_code": "28278", "date": "2024-11-21T13:06:18.823413Z", "url": "https://www.lowes.com/pd/Worth-Imports-1-41-ft-17-in-Pumpkin-Artificial-Wreath/5015355121", "model_number": "9990", "brand": "Worth Imports", "price_hidden_in_cart": false, "price": 48.48},
{"item_id": "5000032075", "store_number": "0416", "zip_code": "28278", "date": "2024-11-21T13:06:20.205596Z", "url": "https://www.lowes.com/pd/Worth-Imports-80-in-Natural-Nuts-and-Cone-Garland/5000032075", "model_number": "5630", "brand": "Worth Imports", "price_hidden_in_cart": false, "price": 19.27},
{"item_id": "5013823281", "store_number": "0416", "zip_code": "28278", "date": "2024-11-21T13:06:21.161785Z", "url": "https://www.lowes.com/pd/Nearly-Natural-24-in-Pumpkin-Artificial-Wreath/5013823281", "model_number": "4902", "brand": "Nearly Natural", "price_hidden_in_cart": false, "price": 87.2},
{"item_id": "5000032069", "store_number": "0416", "zip_code": "28278", "date": "2024-11-21T13:06:22.799365Z", "url": "https://www.lowes.com/pd/Worth-Imports-28-in-Mixed-Fall-Sunflower-Teardrop/5000032069", "model_number": "5212", "brand": "Worth Imports", "price_hidden_in_cart": false, "price": 30},
{"item_id": "5013823169", "store_number": "0416", "zip_code": "28278", "date": "2024-11-21T13:06:23.635872Z", "url": "https://www.lowes.com/pd/Nearly-Natural-6-ft-Harvest-Artificial-Garland/5013823169", "model_number": "W1230", "brand": "Nearly Natural", "price_hidden_in_cart": false, "price": 51.95},
{"item_id": "5015377445", "store_number": "0416", "zip_code": "28278", "date": "2024-11-21T13:06:25.070558Z", "url": "https://www.lowes.com/pd/Sullivans-6-ft-Harvest-Artificial-Garland/5015377445", "model_number": "WGGD BLK", "brand": "Sullivans", "price_hidden_in_cart": false, "price": 45},
{"item_id": "1003202026", "store_number": "0416", "zip_code": "28278", "date": "2024-11-21T13:06:26.404351Z", "url": "https://www.lowes.com/pd/Nearly-Natural-25-in-Sorghum-Harvest-Artificial-Wreath/1003202026", "model_number": "4278", "brand": "Nearly Natural", "price_hidden_in_cart": false, "price": 65.43},
{"item_id": "5015205603", "store_number": "0416", "zip_code": "28278", "date": "2024-11-21T13:06:27.733652Z", "url": "https://www.lowes.com/pd/Northlight-5-ft-Harvest-Artificial-Garland/5015205603", "model_number": "34868444", "brand": "Northlight", "price_hidden_in_cart": false, "price": 47.98},
{"item_id": "5002009145", "store_number": "0416", "zip_code": "28278", "date": "2024-11-21T13:06:28.860815Z", "url": "https://www.lowes.com/pd/Worth-Imports-26-Fall-White-Gourd-Teardrop/5002009145", "model_number": "9902", "brand": "Worth Imports", "price_hidden_in_cart": false, "price": 63},
{"item_id": "1003258838", "store_number": "0416", "zip_code": "28278", "date": "2024-11-21T13:06:29.755400Z", "url": "https://www.lowes.com/pd/Nearly-Natural-20-in-Harvest-Leaf-and-Mini-Pumpkin-Artificial-Wreath/1003258838", "model_number": "4472", "brand": "Nearly Natural", "price_hidden_in_cart": false, "price": 47.05},
{"item_id": "1003258846", "store_number": "0416", "zip_code": "28278", "date": "2024-11-21T13:06:31.315474Z", "url": "https://www.lowes.com/pd/Nearly-Natural-6-ft-Autumn-Magnolia-Leaf-with-Berries-Artificial-Garland/1003258846", "model_number": "4495", "brand": "Nearly Natural", "price_hidden_in_cart": false, "price": 40.42},
{"item_id": "5015205625", "store_number": "0416", "zip_code": "28278", "date": "2024-11-21T13:06:32.646429Z", "url": "https://www.lowes.com/pd/Northlight-0-5-ft-22-in-Harvest-Artificial-Wreath/5015205625", "model_number": "32257212", "brand": "Northlight", "price_hidden_in_cart": false, "price": 95.01},
{"item_id": "5015205637", "store_number": "0416", "zip_code": "28278", "date": "2024-11-21T13:06:34.079801Z", "url": "https://www.lowes.com/pd/Northlight-5-ft-Harvest-Artificial-Garland/5015205637", "model_number": "35762343", "brand": "Northlight", "price_hidden_in_cart": false, "price": 46.98},
{"item_id": "5015377393", "store_number": "0416", "zip_code": "28278", "date": "2024-11-21T13:06:35.387398Z", "url": "https://www.lowes.com/pd/Sullivans-1-2-ft-14-5-in-Harvest-Artificial-Wreath/5015377393", "model_number": "MIF4", "brand": "Sullivans", "price_hidden_in_cart": false, "price": 26.98},
{"item_id": "5015354963", "store_number": "0416", "zip_code": "28278", "date": "2024-11-21T13:06:36.947818Z", "url": "https://www.lowes.com/pd/Worth-Imports-1-25-ft-15-in-Berries-Artificial-Wreath/5015354963", "model_number": "9980", "brand": "Worth Imports", "price_hidden_in_cart": false, "price": 27.98},
{"item_id": "5013823393", "store_number": "0416", "zip_code": "28278", "date": "2024-11-21T13:06:37.715507Z", "url": "https://www.lowes.com/pd/Nearly-Natural-2-5-ft-30-in-Pumpkin-Artificial-Wreath/5013823393", "model_number": "W1192", "brand": "Nearly Natural", "price_hidden_in_cart": false, "price": 86.7},
{"item_id": "5015205631", "store_number": "0416", "zip_code": "28278", "date": "2024-11-21T13:06:40.123358Z", "url": "https://www.lowes.com/pd/Northlight-5-ft-Harvest-Artificial-Garland/5015205631", "model_number": "34868452", "brand": "Northlight", "price_hidden_in_cart": false, "price": 50.98},
{"item_id": "5015354987", "store_number": "0416", "zip_code": "28278", "date": "2024-11-21T13:06:41.250220Z", "url": "https://www.lowes.com/pd/Worth-Imports-1-83-ft-22-in-Pumpkin-Artificial-Wreath/5015354987", "model_number": "12015", "brand": "Worth Imports", "price_hidden_in_cart": false, "price": 68.48},
{"item_id": "5015377371", "store_number": "0416", "zip_code": "28278", "date": "2024-11-21T13:06:42.273241Z", "url": "https://www.lowes.com/pd/Sullivans-1-7-ft-20-5-in-Harvest-Artificial-Wreath/5015377371", "model_number": "MM6", "brand": "Sullivans", "price_hidden_in_cart": false, "price": 35.98},
{"item_id": "5015533207", "store_number": "0416", "zip_code": "28278", "date": "2024-11-21T13:06:43.604943Z", "url": "https://www.lowes.com/pd/Haute-Decor-24-Inch-Fall-Sunflower-Wreath/5015533207", "model_number": "DHWR2401", "brand": "Haute Decor", "price_hidden_in_cart": false, "price": 69.99},
{"item_id": "5013805391", "store_number": "0416", "zip_code": "28278", "date": "2024-11-21T13:06:44.833799Z", "url": "https://www.lowes.com/pd/Worth-Imports-25-in-Heathers-And-Wild-Twigs-Fall-Wreath/5013805391", "model_number": "9933", "brand": "Worth Imports", "price_hidden_in_cart": false, "price": 37.83},
{"item_id": "5015205571", "store_number": "0416", "zip_code": "28278", "date": "2024-11-21T13:06:46.164579Z", "url": "https://www.lowes.com/pd/Northlight-5-ft-Harvest-Artificial-Garland/5015205571", "model_number": "35762376", "brand": "Northlight", "price_hidden_in_cart": false, "price": 46.98},
{"item_id": "5014356705", "store_number": "0416", "zip_code": "28278", "date": "2024-11-21T13:06:47.232548Z", "url": "https://www.lowes.com/pd/Northlight-24-in-Purple-Indoor-Hanging-Artificial-Wreath/5014356705", "model_number": "35644459", "brand": "Northlight", "price_hidden_in_cart": false, "price": 85.48},
{"item_id": "5015533183", "store_number": "0416", "zip_code": "28278", "date": "2024-11-21T13:06:48.621722Z", "url": "https://www.lowes.com/pd/Haute-Decor-32-Inch-Fall-Sunflower-Swag/5015533183", "model_number": "DHSW3201", "brand": "Haute Decor", "price_hidden_in_cart": false, "price": 69.99},
{"item_id": "5013548387", "store_number": "0416", "zip_code": "28278", "date": "2024-11-21T13:06:49.442800Z", "url": "https://www.lowes.com/pd/Nearly-Natural-6-ft-Gourd-Artificial-Garland/5013548387", "model_number": "W1217", "brand": "Nearly Natural", "price_hidden_in_cart": false, "price": 55.48},
{"item_id": "5015205619", "store_number": "0416", "zip_code": "28278", "date": "2024-11-21T13:06:52.001441Z", "url": "https://www.lowes.com/pd/Northlight-0-5-ft-24-in-Harvest-Artificial-Wreath/5015205619", "model_number": "35762342", "brand": "Northlight", "price_hidden_in_cart": false, "price": 61.98},
{"item_id": "1000793028", "store_number": "0416", "zip_code": "28278", "date": "2024-11-21T13:06:52.031748Z", "url": "https://www.lowes.com/pd/Nearly-Natural-30-in-Autumn-Indoor-Leaf-Artificial-Thanksgiving-Wreath/1000793028", "model_number": "4908", "brand": "Nearly Natural", "price_hidden_in_cart": false, "price": 68.61},
{"item_id": "5013823293", "store_number": "0416", "zip_code": "28278", "date": "2024-11-21T13:06:53.435346Z", "url": "https://www.lowes.com/pd/Nearly-Natural-2-5-ft-30-in-Harvest-Artificial-Wreath/5013823293", "model_number": "W1187", "brand": "Nearly Natural", "price_hidden_in_cart": false, "price": 73.91},
{"item_id": "5013823217", "store_number": "0416", "zip_code": "28278", "date": "2024-11-21T13:06:54.664810Z", "url": "https://www.lowes.com/pd/Nearly-Natural-2-1-ft-25-in-Harvest-Artificial-Wreath/5013823217", "model_number": "W1229", "brand": "Nearly Natural", "price_hidden_in_cart": false, "price": 54.14},
{"item_id": "5013801495", "store_number": "0416", "zip_code": "28278", "date": "2024-11-21T13:06:55.999465Z", "url": "https://www.lowes.com/pd/Northlight-13-in-Orange-Artificial-Fall-Harvest-Wreath-with-Pumpkins-Berries-and-Pinecones-Sturdy-Twig-Backing-Indoor-Thanksgiving-Decor/5013801495", "model_number": "34141523", "brand": "Northlight", "price_hidden_in_cart": false, "price": 28.48},
{"item_id": "5014356729", "store_number": "0416", "zip_code": "28278", "date": "2024-11-21T13:06:57.430953Z", "url": "https://www.lowes.com/pd/Northlight-15-in-Purple-Indoor-Hanging-Artificial-Wreath/5014356729", "model_number": "34808684", "brand": "Northlight", "price_hidden_in_cart": false, "price": 32.98},
{"item_id": "5012907183", "store_number": "0416", "zip_code": "28278", "date": "2024-11-21T13:06:58.348723Z", "url": "https://www.lowes.com/pd/Puleo-International-2-5-ft-30-in-Artificial-Wreath/5012907183", "model_number": "305-1291A-W30", "brand": "Puleo International", "price_hidden_in_cart": false, "price": 174.7},
{"item_id": "5013823275", "store_number": "0416", "zip_code": "28278", "date": "2024-11-21T13:06:59.060254Z", "url": "https://www.lowes.com/pd/Nearly-Natural-2-2-ft-26-in-Pumpkin-Artificial-Wreath/5013823275", "model_number": "W1189", "brand": "Nearly Natural", "price_hidden_in_cart": false, "price": 66.09},
{"item_id": "1003258852", "store_number": "0416", "zip_code": "28278", "date": "2024-11-21T13:07:00.193957Z", "url": "https://www.lowes.com/pd/Nearly-Natural-35-in-Fall-Magnolia-Leaf-Artificial-Swag/1003258852", "model_number": "4646", "brand": "Nearly Natural", "price_hidden_in_cart": false, "price": 30.86},
{"item_id": "5014356689", "store_number": "0416", "zip_code": "28278", "date": "2024-11-21T13:07:01.217870Z", "url": "https://www.lowes.com/pd/Northlight-18-in-Purple-Indoor-Hanging-Artificial-Wreath/5014356689", "model_number": "34808685", "brand": "Northlight", "price_hidden_in_cart": false, "price": 44.98},
{"item_id": "5013935237", "store_number": "0416", "zip_code": "28278", "date": "2024-11-21T13:07:02.243064Z", "url": "https://www.lowes.com/pd/National-Tree-Company-2-5-ft-30-in-Harvest-Artificial-Wreath/5013935237", "model_number": "RAHV-20101012W", "brand": "National Tree Company", "price_hidden_in_cart": false, "price": 92.14},
{"item_id": "5014595063", "store_number": "0416", "zip_code": "28278", "date": "2024-11-21T13:07:03.777183Z", "url": "https://www.lowes.com/pd/Worth-Imports-1-66-ft-20-in-Leaves-Artificial-Wreath/5014595063", "model_number": "9969", "brand": "Worth Imports", "price_hidden_in_cart": false, "price": 50.48},
{"item_id": "5013548481", "store_number": "0416", "zip_code": "28278", "date": "2024-11-21T13:07:05.212656Z", "url": "https://www.lowes.com/pd/Nearly-Natural-2-5-ft-30-in-Sunflowers-Artificial-Wreath/5013548481", "model_number": "W1179", "brand": "Nearly Natural", "price_hidden_in_cart": false, "price": 90.77},
{"item_id": "5014595031", "store_number": "0416", "zip_code": "28278", "date": "2024-11-21T13:07:06.541977Z", "url": "https://www.lowes.com/pd/Worth-Imports-1-08-ft-13-in-Leaves-Artificial-Wreath/5014595031", "model_number": "9960", "brand": "Worth Imports", "price_hidden_in_cart": false, "price": 37.98},
{"item_id": "5013801563", "store_number": "0416", "zip_code": "28278", "date": "2024-11-21T13:07:08.285148Z", "url": "https://www.lowes.com/pd/Northlight-24-in-Orange-Autumn-Harvest-Thanksgiving-Foliage-Wreath-with-Pumpkin-Sunflower-Berries-and-Pine-Cones-Artificial-Twig-Backing/5013801563", "model_number": "34141521", "brand": "Northlight", "price_hidden_in_cart": false, "price": 56.48},
{"item_id": "5004299049", "store_number": "0416", "zip_code": "28278", "date": "2024-11-21T13:07:10.025015Z", "url": "https://www.lowes.com/pd/National-Tree-Company/5004299049", "model_number": "HC7-104L-36W", "brand": "National Tree Company", "price_hidden_in_cart": false, "price": 86.98},
{"item_id": "5015205649", "store_number": "0416", "zip_code": "28278", "date": "2024-11-21T13:07:10.318808Z", "url": "https://www.lowes.com/pd/Northlight-0-5-ft-10-in-Harvest-Artificial-Wreath/5015205649", "model_number": "33530749", "brand": "Northlight", "price_hidden_in_cart": false, "price": 27.89},
{"item_id": "1003258844", "store_number": "0416", "zip_code": "28278", "date": "2024-11-21T13:07:11.294707Z", "url": "https://www.lowes.com/pd/Nearly-Natural-36-in-Autumn-Magnolia-Leaf-with-Berries-Artificial-Tear-Drop/1003258844", "model_number": "4494", "brand": "Nearly Natural", "price_hidden_in_cart": false, "price": 31.32},
{"item_id": "5013823171", "store_number": "0416", "zip_code": "28278", "date": "2024-11-21T13:07:12.206471Z", "url": "https://www.lowes.com/pd/Nearly-Natural-2-ft-24-in-Harvest-Artificial-Wreath/5013823171", "model_number": "W1122", "brand": "Nearly Natural", "price_hidden_in_cart": false, "price": 80.35},
{"item_id": "5015731087", "store_number": "0416", "zip_code": "28278", "date": "2024-11-21T13:07:13.102556Z", "url": "https://www.lowes.com/pd/22-inch-Sunflower-Wreath/5015731087", "model_number": "MFGWF5976X22X", "brand": null, "price_hidden_in_cart": false, "price": 49.99},
{"item_id": "5015161581", "store_number": "0416", "zip_code": "28278", "date": "2024-11-21T13:07:14.186151Z", "url": "https://www.lowes.com/pd/Sullivans-2-ft-24-in-Leaves-Artificial-Wreath/5015161581", "model_number": "02299WR", "brand": "Sullivans", "price_hidden_in_cart": false, "price": 80.98},
{"item_id": "5015205589", "store_number": "0416", "zip_code": "28278", "date": "2024-11-21T13:07:15.143716Z", "url": "https://www.lowes.com/pd/Northlight-2-67-ft-32-in-Harvest-Artificial-Wreath/5015205589", "model_number": "34303452", "brand": "Northlight", "price_hidden_in_cart": false, "price": 65.69},
{"item_id": "5013823339", "store_number": "0416", "zip_code": "28278", "date": "2024-11-21T13:07:20.366564Z", "url": "https://www.lowes.com/pd/Nearly-Natural-1-8-ft-22-in-Pumpkin-Artificial-Wreath/5013823339", "model_number": "W1259", "brand": "Nearly Natural", "price_hidden_in_cart": false, "price": 54.93},
{"item_id": "5015354803", "store_number": "0416", "zip_code": "28278", "date": "2024-11-21T13:07:23.440767Z", "url": "https://www.lowes.com/pd/Glitzhome-2-ft-24-in-Sunflowers-Artificial-Wreath/5015354803", "model_number": "2006300035", "brand": "Glitzhome", "price_hidden_in_cart": false, "price": 63.98},
{"item_id": "5015205691", "store_number": "0416", "zip_code": "28278", "date": "2024-11-21T13:07:23.938823Z", "url": "https://www.lowes.com/pd/Northlight-3-67-ft-22-in-Harvest-Artificial-Wreath/5015205691", "model_number": "35182618", "brand": "Northlight", "price_hidden_in_cart": false, "price": 74.98},
{"item_id": "5013935241", "store_number": "0416", "zip_code": "28278", "date": "2024-11-21T13:07:25.501587Z", "url": "https://www.lowes.com/pd/National-Tree-Company-2-7-ft-32-in-Harvest-Artificial-Wreath/5013935241", "model_number": "RAHV-20101020W", "brand": "National Tree Company", "price_hidden_in_cart": false, "price": 95.64},
{"item_id": "5015377465", "store_number": "0416", "zip_code": "28278", "date": "2024-11-21T13:07:26.820358Z", "url": "https://www.lowes.com/pd/Sullivans-1-2-ft-14-in-Pumpkin-Artificial-Wreath/5015377465", "model_number": "FPM6", "brand": "Sullivans", "price_hidden_in_cart": false, "price": 32.98},
{"item_id": "5015355149", "store_number": "0416", "zip_code": "28278", "date": "2024-11-21T13:07:28.047679Z", "url": "https://www.lowes.com/pd/Worth-Imports-5-41-ft-Leaves-Artificial-Garland/5015355149", "model_number": "9127", "brand": "Worth Imports", "price_hidden_in_cart": false, "price": 24.48},
{"item_id": "5015355043", "store_number": "0416", "zip_code": "28278", "date": "2024-11-21T13:07:29.189534Z", "url": "https://www.lowes.com/pd/Worth-Imports-1-75-ft-21-in-Berries-Artificial-Wreath/5015355043", "model_number": "12019", "brand": "Worth Imports", "price_hidden_in_cart": false, "price": 50.48},
{"item_id": "5014356707", "store_number": "0416", "zip_code": "28278", "date": "2024-11-21T13:07:30.506065Z", "url": "https://www.lowes.com/pd/Northlight-24-in-Purple-Indoor-Hanging-Artificial-Wreath/5014356707", "model_number": "35644464", "brand": "Northlight", "price_hidden_in_cart": false, "price": 76.98},
{"item_id": "5013548377", "store_number": "0416", "zip_code": "28278", "date": "2024-11-21T13:07:31.838095Z", "url": "https://www.lowes.com/pd/Nearly-Natural-24-in-Pumpkin-Artificial-Wreath/5013548377", "model_number": "W1218", "brand": "Nearly Natural", "price_hidden_in_cart": false, "price": 48.22},
{"item_id": "5015205645", "store_number": "0416", "zip_code": "28278", "date": "2024-11-21T13:07:33.271612Z", "url": "https://www.lowes.com/pd/Northlight-5-ft-Harvest-Artificial-Garland/5015205645", "model_number": "34868443", "brand": "Northlight", "price_hidden_in_cart": false, "price": 47.98},
{"item_id": "5015205679", "store_number": "0416", "zip_code": "28278", "date": "2024-11-21T13:07:34.293328Z", "url": "https://www.lowes.com/pd/Northlight-0-5-ft-24-in-Harvest-Artificial-Wreath/5015205679", "model_number": "35688252", "brand": "Northlight", "price_hidden_in_cart": false, "price": 84.98},
{"item_id": "1000795388", "store_number": "0416", "zip_code": "28278", "date": "2024-11-21T13:07:35.797298Z", "url": "https://www.lowes.com/pd/Nearly-Natural-24-in-Multicolor-Indoor-Leaf-Artificial-Thanksgiving-Wreath/1000795388", "model_number": "4810", "brand": "Nearly Natural", "price_hidden_in_cart": false, "price": 68.61},
{"item_id": "5015205547", "store_number": "0416", "zip_code": "28278", "date": "2024-11-21T13:07:36.852590Z", "url": "https://www.lowes.com/pd/Northlight-0-5-ft-22-in-Harvest-Artificial-Wreath/5015205547", "model_number": "34868421", "brand": "Northlight", "price_hidden_in_cart": false, "price": 50.98},
{"item_id": "5013823347", "store_number": "0416", "zip_code": "28278", "date": "2024-11-21T13:07:38.085098Z", "url": "https://www.lowes.com/pd/Nearly-Natural-2-ft-24-in-Harvest-Artificial-Wreath/5013823347", "model_number": "W1255", "brand": "Nearly Natural", "price_hidden_in_cart": false, "price": 64.98},
{"item_id": "5015205671", "store_number": "0416", "zip_code": "28278", "date": "2024-11-21T13:07:39.621154Z", "url": "https://www.lowes.com/pd/Northlight-0-5-ft-24-in-Harvest-Artificial-Wreath/5015205671", "model_number": "35688254", "brand": "Northlight", "price_hidden_in_cart": false, "price": 81.98},
{"item_id": "5014595049", "store_number": "0416", "zip_code": "28278", "date": "2024-11-21T13:07:40.951756Z", "url": "https://www.lowes.com/pd/Worth-Imports-2-16-ft-26-in-Sunflowers-Artificial-Wreath/5014595049", "model_number": "9976", "brand": "Worth Imports", "price_hidden_in_cart": false, "price": 56.98},
{"item_id": "5013823279", "store_number": "0416", "zip_code": "28278", "date": "2024-11-21T13:07:42.078982Z", "url": "https://www.lowes.com/pd/Nearly-Natural-2-ft-24-in-Harvest-Artificial-Wreath/5013823279", "model_number": "W1121", "brand": "Nearly Natural", "price_hidden_in_cart": false, "price": 80.35},
{"item_id": "5015731075", "store_number": "0416", "zip_code": "28278", "date": "2024-11-21T13:07:43.408339Z", "url": "https://www.lowes.com/pd/24-inch-Wreath-with-Ruscus-and-Oak-Leaves/5015731075", "model_number": "MFGWF5802X24X", "brand": null, "price_hidden_in_cart": false, "price": 37.99},
{"item_id": "5015205711", "store_number": "0416", "zip_code": "28278", "date": "2024-11-21T13:07:44.841330Z", "url": "https://www.lowes.com/pd/Northlight-1-83-ft-22-in-Harvest-Artificial-Wreath/5015205711", "model_number": "34316662", "brand": "Northlight", "price_hidden_in_cart": false, "price": 49.98},
{"item_id": "5013823357", "store_number": "0416", "zip_code": "28278", "date": "2024-11-21T13:07:46.175873Z", "url": "https://www.lowes.com/pd/Nearly-Natural-2-2-ft-26-in-Pumpkin-Artificial-Wreath/5013823357", "model_number": "W1188", "brand": "Nearly Natural", "price_hidden_in_cart": false, "price": 68.98},
{"item_id": "5001995581", "store_number": "0416", "zip_code": "28278", "date": "2024-11-21T13:07:47.507534Z", "url": "https://www.lowes.com/pd/National-Tree-Company-20-in-Outdoor-White-Pinecones-Artificial-Christmas-Wreath/5001995581", "model_number": "RAHV-W060669A", "brand": "National Tree Company", "price_hidden_in_cart": false, "price": 63.95},
{"item_id": "5013805321", "store_number": "0416", "zip_code": "28278", "date": "2024-11-21T13:07:49.041947Z", "url": "https://www.lowes.com/pd/Worth-Imports-18-in-Fall-Leaves-Pumpkin-Berries-Cornucopia-Wreath/5013805321", "model_number": "9945", "brand": "Worth Imports", "price_hidden_in_cart": false, "price": 63.04},
{"item_id": "5013823207", "store_number": "0416", "zip_code": "28278", "date": "2024-11-21T13:07:50.065945Z", "url": "https://www.lowes.com/pd/Nearly-Natural-2-9-ft-Harvest-Artificial-Swag/5013823207", "model_number": "W1228", "brand": "Nearly Natural", "price_hidden_in_cart": false, "price": 37.7},
{"item_id": "5015205621", "store_number": "0416", "zip_code": "28278", "date": "2024-11-21T13:07:51.394377Z", "url": "https://www.lowes.com/pd/Northlight-0-5-ft-24-in-Harvest-Artificial-Wreath/5015205621", "model_number": "35688253", "brand": "Northlight", "price_hidden_in_cart": false, "price": 81.98},
{"item_id": "5004299601", "store_number": "0416", "zip_code": "28278", "date": "2024-11-21T13:07:52.624428Z", "url": "https://www.lowes.com/pd/National-Tree-Company-0-5-ft-24-in-Harvest-Artificial-Wreath/5004299601", "model_number": "RAHV-SW060135A", "brand": "National Tree Company", "price_hidden_in_cart": false, "price": 45.29},
{"item_id": "5000119953", "store_number": "0416", "zip_code": "28278", "date": "2024-11-21T13:07:53.749976Z", "url": "https://www.lowes.com/pd/Worth-Imports-24-in-Wild-Fall-Leaf-Twig-Wreath/5000119953", "model_number": "7387", "brand": "Worth Imports", "price_hidden_in_cart": false, "price": 45},
{"item_id": "1003258850", "store_number": "0416", "zip_code": "28278", "date": "2024-11-21T13:07:54.978428Z", "url": "https://www.lowes.com/pd/Nearly-Natural-30-in-Fall-Magnolia-Leaf-and-Berries-Artificial-Wreath/1003258850", "model_number": "4498", "brand": "Nearly Natural", "price_hidden_in_cart": false, "price": 59.3}
]